{"per_page":20,"total":1,"current":1,"data":[{"year":"2019","months":[{"month":"1","entries":[{"title":"我的2018流水账","date":"2019-01-29T10:31:19.000Z","slug":"2018-summary"},{"title":"vue更新数据后视图没有刷新的问题","date":"2019-01-24T03:23:56.000Z","slug":"vue-model-view"}]}]},{"year":"2018","months":[{"month":"9","entries":[{"title":"Vue组件间的通信","date":"2018-09-07T12:39:21.000Z","slug":"vue-component-communication"}]},{"month":"6","entries":[{"title":"关于cookie、session和HTTP缓存","date":"2018-06-22T14:18:26.000Z","slug":"cookie-session-http-cache"}]},{"month":"5","entries":[{"title":"理解JS中的闭包","date":"2018-05-19T06:51:03.000Z","slug":"js-closure"},{"title":"JS中的call、apply、bind","date":"2018-05-10T14:18:26.000Z","slug":"call-apply-bind"}]},{"month":"4","entries":[{"title":"移动端Web页面适配方案","date":"2018-04-25T16:00:00.000Z","slug":"mobile-web-adaptation"},{"title":"从输入URL到页面加载完成的过程中都发生了什么","date":"2018-04-24T16:00:00.000Z","slug":"from-url-page"},{"title":"JavaScript常见原生DOM操作API总结","date":"2018-04-05T13:38:39.000Z","slug":"dom-api"}]},{"month":"3","entries":[{"title":"为博客添加Gitalk评论插件","date":"2018-03-21T18:32:49.000Z","slug":"hexo-gitalk"},{"title":"博客从Firekylin迁移到Hexo","date":"2018-03-20T16:00:00.000Z","slug":"firekylin-hexo"},{"title":"【笔记】 vim命令大全","date":"2018-03-20T03:39:21.000Z","slug":"vim-command"},{"title":"使用JS和Canvas做一个画板","date":"2018-03-10T17:22:14.000Z","slug":"drawing-borad"},{"title":"HTML5 Canvas 基础","date":"2018-03-05T15:21:54.000Z","slug":"html5-canvas"}]},{"month":"2","entries":[{"title":"堆排序解析及JavaScript实现","date":"2018-02-27T17:35:21.000Z","slug":"heap-sort"},{"title":"计数排序解析及JavaScript实现","date":"2018-02-26T14:32:45.000Z","slug":"count-sort"}]},{"month":"1","entries":[{"title":"JS函数节流(throttle)与函数去抖(debounce)","date":"2018-01-18T13:23:43.000Z","slug":"js-throttle-debounce"}]}]},{"year":"2017","months":[{"month":"10","entries":[{"title":"CSS多行文本溢出省略显示","date":"2017-10-13T12:52:21.000Z","slug":"text-overflow"}]}]},{"year":"2016","months":[{"month":"10","entries":[{"title":"test","date":"2016-10-13T12:52:21.000Z","slug":"test"}]}]}]}